advanced_print/__init__.py
advanced_print/logger.py
advanced_print-0.1.5.dist-info/LICENSE
advanced_print-0.1.5.dist-info/METADATA
advanced_print-0.1.5.dist-info/WHEEL
advanced_print-0.1.5.dist-info/RECORD
