Metadata-Version: 2.1
Name: advanced-print
Version: 0.1.5
Summary: 
Author: Alpha
Author-email: piotr@piotryordanov.com
Requires-Python: >=3.9,<4.0
Classifier: Programming Language :: Python :: 3
Classifier: Programming Language :: Python :: 3.9
Classifier: Programming Language :: Python :: 3.10
Classifier: Programming Language :: Python :: 3.11
Classifier: Programming Language :: Python :: 3.12
